{
    "indicateur": "répartition des epma par forme juridique",
    "data": [
        {
            "forme_juridique": "SARL",
            "region": "marrakech-safi",
            "annuel": "2020",
            "valeur": 19455
        },
        {
            "forme_juridique": "SARL-AU",
            "region": "marrakech-safi",
            "annuel": "2020",
            "valeur": 12655
        },
        {
            "forme_juridique": "SA",
            "region": "marrakech-safi",
            "annuel": "2020",
            "valeur": 489
        },
        {
            "forme_juridique": "Autres",
            "region": "marrakech-safi",
            "annuel": "2020",
            "valeur": 1039
        },
        {
            "forme_juridique": "Total",
            "region": "marrakech-safi",
            "annuel": "2020",
            "valeur": 33638
        },
        {
            "forme_juridique": "SARL",
            "region": "marrakech-safi",
            "annuel": "2021",
            "valeur": 19795
        },
        {
            "forme_juridique": "SARL-AU",
            "region": "marrakech-safi",
            "annuel": "2021",
            "valeur": 15143
        },
        {
            "forme_juridique": "SA",
            "region": "marrakech-safi",
            "annuel": "2021",
            "valeur": 501
        },
        {
            "forme_juridique": "Autres",
            "region": "marrakech-safi",
            "annuel": "2021",
            "valeur": 1159
        },
        {
            "forme_juridique": "Total",
            "region": "marrakech-safi",
            "annuel": "2021",
            "valeur": 36598
        }
    ]
}