[
    {
        "tbDomaine": "Offre de travail - décisionnel",
        "categorie": "nouveaux entrants potentiels sur le marché du travail",
        "indicateur": "nouveaux entrants potentiels sur le mt par genre"
    },
    {
        "tbDomaine": "Offre de travail - décisionnel",
        "categorie": "nouveaux entrants potentiels sur le marché du travail",
        "indicateur": "nouveaux entrants potentiels sur le mt par composante"
    },
    {
        "tbDomaine": "Offre de travail - décisionnel",
        "categorie": "activité",
        "indicateur": "population en âge d’activité"
    },
    {
        "tbDomaine": "Offre de travail - décisionnel",
        "categorie": "activité",
        "indicateur": "population inactive"
    },
    {
        "tbDomaine": "Offre de travail - décisionnel",
        "categorie": "activité",
        "indicateur": "population active"
    },
    {
        "tbDomaine": "Offre de travail - décisionnel",
        "categorie": "activité",
        "indicateur": "population active par diplôme et milieu"
    },
    {
        "tbDomaine": "Offre de travail - décisionnel",
        "categorie": "activité",
        "indicateur": "population en active par diplôme et milieu de résidence"
    },
    {
        "tbDomaine": "Offre de travail - décisionnel",
        "categorie": "activité",
        "indicateur": "taux d’activité selon le genre et le milieu de résidence"
    },
    {
        "tbDomaine": "Offre de travail - décisionnel",
        "categorie": "activité",
        "indicateur": "taux d’activité selon le genre"
    },
    {
        "tbDomaine": "Offre de travail - décisionnel",
        "categorie": "activité",
        "indicateur": "taux d’activité selon le groupe d’âge et le milieu de résidence"
    },
    {
        "tbDomaine": "Offre de travail - décisionnel",
        "categorie": "activité",
        "indicateur": "taux d’activité selon le groupe d’âge et le genre"
    },
    {
        "tbDomaine": "Offre de travail - décisionnel",
        "categorie": "activité",
        "indicateur": "taux d’activité selon le diplôme et le milieu de résidence"
    },
    {
        "tbDomaine": "Offre de travail - décisionnel",
        "categorie": "activité",
        "indicateur": "taux d’activité selon le diplôme et le genre"
    },
    {
        "tbDomaine": "Offre de travail - décisionnel",
        "categorie": "activité",
        "indicateur": "taux d’activité selon le milieu de résidence"
    },
    {
        "tbDomaine": "Offre de travail - décisionnel",
        "categorie": "activité",
        "indicateur": "taux d’activité par région et le milieu de résidence"
    },
    {
        "tbDomaine": "Offre de travail - décisionnel",
        "categorie": "activité",
        "indicateur": "taux d’activité par région et genre"
    },
    {
        "tbDomaine": "Offre de travail - décisionnel",
        "categorie": "chômage ",
        "indicateur": "population active en chômage par milieu de résidence"
    },
    {
        "tbDomaine": "Offre de travail - décisionnel",
        "categorie": "chômage ",
        "indicateur": "population active en chômage par diplôme et genre"
    },
    {
        "tbDomaine": "Offre de travail - décisionnel",
        "categorie": "chômage ",
        "indicateur": "population active en chômage par diplôme et milieu de résidence"
    },
    {
        "tbDomaine": "Offre de travail - décisionnel",
        "categorie": "chômage ",
        "indicateur": "population active en chômage par genre"
    },
    {
        "tbDomaine": "Offre de travail - décisionnel",
        "categorie": "chômage ",
        "indicateur": "population active en chômage selon la durée"
    },
    {
        "tbDomaine": "Offre de travail - décisionnel",
        "categorie": "chômage ",
        "indicateur": "population active en chômage selon l’expérience"
    },
    {
        "tbDomaine": "Offre de travail - décisionnel",
        "categorie": "chômage ",
        "indicateur": "population active en chômage selon les causes"
    },
    {
        "tbDomaine": "Offre de travail - décisionnel",
        "categorie": "chômage ",
        "indicateur": "taux de chômage selon le milieu de résidence"
    },
    {
        "tbDomaine": "Offre de travail - décisionnel",
        "categorie": "chômage ",
        "indicateur": "taux de chômage par région et genre"
    },
    {
        "tbDomaine": "Offre de travail - décisionnel",
        "categorie": "chômage ",
        "indicateur": "taux de chômage par région et milieu de résidence"
    },
    {
        "tbDomaine": "Offre de travail - décisionnel",
        "categorie": "chômage ",
        "indicateur": "taux de chômage selon le groupe d’âge"
    },
    {
        "tbDomaine": "Offre de travail - décisionnel",
        "categorie": "chômage ",
        "indicateur": "taux de chômage selon le diplôme"
    },
    {
        "tbDomaine": "Offre de travail - décisionnel",
        "categorie": "chômage ",
        "indicateur": "taux de chômage selon le genre"
    },
    {
        "tbDomaine": "Offre de travail - décisionnel",
        "categorie": "neet",
        "indicateur": "effectif des jeunes neet par milieu de résidence"
    },
    {
        "tbDomaine": "Offre de travail - décisionnel",
        "categorie": "neet",
        "indicateur": "effectif des jeunes neet par genre"
    },
    {
        "tbDomaine": "Offre de travail - décisionnel",
        "categorie": "neet",
        "indicateur": "taux de neet par milieu de résidence"
    },
    {
        "tbDomaine": "Offre de travail - décisionnel",
        "categorie": "neet",
        "indicateur": "taux de neet par genre"
    },
    {
        "tbDomaine": "Offre de travail - décisionnel",
        "categorie": "neet",
        "indicateur": "taux de neet par région"
    }
]