{
    "indicateur": "productivité par secteur d’activité",
    "data": [
        {
            "secteur_activite": "AGRICOLE",
            "region": "Tanger-Tétouan-Al Hoceima",
            "annuel": "2019",
            "valeur": 39010
        },
        {
            "secteur_activite": "AGRICOLE",
            "region": "Oriental",
            "annuel": "2019",
            "valeur": 50302
        },
        {
            "secteur_activite": "AGRICOLE",
            "region": "Fès-Meknès",
            "annuel": "2019",
            "valeur": 41935
        },
        {
            "secteur_activite": "AGRICOLE",
            "region": "Rabat-Salé-Kénitra",
            "annuel": "2019",
            "valeur": 55893
        },
        {
            "secteur_activite": "AGRICOLE",
            "region": "Béni Mellal-Khénifra",
            "annuel": "2019",
            "valeur": 29893
        },
        {
            "secteur_activite": "AGRICOLE",
            "region": "Casablanca-Settat",
            "annuel": "2019",
            "valeur": 26389
        },
        {
            "secteur_activite": "AGRICOLE",
            "region": "Marrakech-Safi",
            "annuel": "2019",
            "valeur": 22587
        },
        {
            "secteur_activite": "AGRICOLE",
            "region": "Drâa-Tafilalet",
            "annuel": "2019",
            "valeur": 37221
        },
        {
            "secteur_activite": "AGRICOLE",
            "region": "Souss-Massa",
            "annuel": "2019",
            "valeur": 58280
        },
        {
            "secteur_activite": "AGRICOLE",
            "region": "Régions du Sud",
            "annuel": "2019",
            "valeur": 64909
        },
        {
            "secteur_activite": "NON AGRICOLE",
            "region": "Tanger-Tétouan-Al Hoceima",
            "annuel": "2019",
            "valeur": 148344
        },
        {
            "secteur_activite": "NON AGRICOLE",
            "region": "Oriental",
            "annuel": "2019",
            "valeur": 99333
        },
        {
            "secteur_activite": "NON AGRICOLE",
            "region": "Fès-Meknès",
            "annuel": "2019",
            "valeur": 89543
        },
        {
            "secteur_activite": "NON AGRICOLE",
            "region": "Rabat-Salé-Kénitra",
            "annuel": "2019",
            "valeur": 144923
        },
        {
            "secteur_activite": "NON AGRICOLE",
            "region": "Béni Mellal-Khénifra",
            "annuel": "2019",
            "valeur": 120669
        },
        {
            "secteur_activite": "NON AGRICOLE",
            "region": "Casablanca-Settat",
            "annuel": "2019",
            "valeur": 173927
        },
        {
            "secteur_activite": "NON AGRICOLE",
            "region": "Marrakech-Safi",
            "annuel": "2019",
            "valeur": 89117
        },
        {
            "secteur_activite": "NON AGRICOLE",
            "region": "Drâa-Tafilalet",
            "annuel": "2019",
            "valeur": 94286
        },
        {
            "secteur_activite": "NON AGRICOLE",
            "region": "Souss-Massa",
            "annuel": "2019",
            "valeur": 102761
        },
        {
            "secteur_activite": "NON AGRICOLE",
            "region": "Régions du Sud",
            "annuel": "2019",
            "valeur": 215255
        },
        {
            "secteur_activite": "AGRICOLE",
            "region": "Tanger-Tétouan-Al Hoceima",
            "annuel": "2020",
            "valeur": 37547
        },
        {
            "secteur_activite": "AGRICOLE",
            "region": "Oriental",
            "annuel": "2020",
            "valeur": 64794
        },
        {
            "secteur_activite": "AGRICOLE",
            "region": "Fès-Meknès",
            "annuel": "2020",
            "valeur": 44226
        },
        {
            "secteur_activite": "AGRICOLE",
            "region": "Rabat-Salé-Kénitra",
            "annuel": "2020",
            "valeur": 55542
        },
        {
            "secteur_activite": "AGRICOLE",
            "region": "Béni Mellal-Khénifra",
            "annuel": "2020",
            "valeur": 31509
        },
        {
            "secteur_activite": "AGRICOLE",
            "region": "Casablanca-Settat",
            "annuel": "2020",
            "valeur": 23118
        },
        {
            "secteur_activite": "AGRICOLE",
            "region": "Marrakech-Safi",
            "annuel": "2020",
            "valeur": 19525
        },
        {
            "secteur_activite": "AGRICOLE",
            "region": "Drâa-Tafilalet",
            "annuel": "2020",
            "valeur": 44565
        },
        {
            "secteur_activite": "AGRICOLE",
            "region": "Souss-Massa",
            "annuel": "2020",
            "valeur": 53164
        },
        {
            "secteur_activite": "AGRICOLE",
            "region": "Régions du Sud",
            "annuel": "2020",
            "valeur": 94871
        },
        {
            "secteur_activite": "NON AGRICOLE",
            "region": "Tanger-Tétouan-Al Hoceima",
            "annuel": "2020",
            "valeur": 132229
        },
        {
            "secteur_activite": "NON AGRICOLE",
            "region": "Oriental",
            "annuel": "2020",
            "valeur": 96934
        },
        {
            "secteur_activite": "NON AGRICOLE",
            "region": "Fès-Meknès",
            "annuel": "2020",
            "valeur": 83104
        },
        {
            "secteur_activite": "NON AGRICOLE",
            "region": "Rabat-Salé-Kénitra",
            "annuel": "2020",
            "valeur": 141651
        },
        {
            "secteur_activite": "NON AGRICOLE",
            "region": "Béni Mellal-Khénifra",
            "annuel": "2020",
            "valeur": 111444
        },
        {
            "secteur_activite": "NON AGRICOLE",
            "region": "Casablanca-Settat",
            "annuel": "2020",
            "valeur": 174253
        },
        {
            "secteur_activite": "NON AGRICOLE",
            "region": "Marrakech-Safi",
            "annuel": "2020",
            "valeur": 75932
        },
        {
            "secteur_activite": "NON AGRICOLE",
            "region": "Drâa-Tafilalet",
            "annuel": "2020",
            "valeur": 88955
        },
        {
            "secteur_activite": "NON AGRICOLE",
            "region": "Souss-Massa",
            "annuel": "2020",
            "valeur": 95014
        },
        {
            "secteur_activite": "NON AGRICOLE",
            "region": "Régions du Sud",
            "annuel": "2020",
            "valeur": 218962
        },
        {
            "secteur_activite": "AGRICOLE",
            "region": "Tanger-Tétouan-Al Hoceima",
            "annuel": "2021",
            "valeur": 26702
        },
        {
            "secteur_activite": "AGRICOLE",
            "region": "Oriental",
            "annuel": "2021",
            "valeur": 65711
        },
        {
            "secteur_activite": "AGRICOLE",
            "region": "Fès-Meknès",
            "annuel": "2021",
            "valeur": 61428
        },
        {
            "secteur_activite": "AGRICOLE",
            "region": "Rabat-Salé-Kénitra",
            "annuel": "2021",
            "valeur": 67291
        },
        {
            "secteur_activite": "AGRICOLE",
            "region": "Béni Mellal-Khénifra",
            "annuel": "2021",
            "valeur": 43907
        },
        {
            "secteur_activite": "AGRICOLE",
            "region": "Casablanca-Settat",
            "annuel": "2021",
            "valeur": 45126
        },
        {
            "secteur_activite": "AGRICOLE",
            "region": "Marrakech-Safi",
            "annuel": "2021",
            "valeur": 29104
        },
        {
            "secteur_activite": "AGRICOLE",
            "region": "Drâa-Tafilalet",
            "annuel": "2021",
            "valeur": 47825
        },
        {
            "secteur_activite": "AGRICOLE",
            "region": "Souss-Massa",
            "annuel": "2021",
            "valeur": 74353
        },
        {
            "secteur_activite": "AGRICOLE",
            "region": "Régions du Sud",
            "annuel": "2021",
            "valeur": 111840
        },
        {
            "secteur_activite": "NON AGRICOLE",
            "region": "Tanger-Tétouan-Al Hoceima",
            "annuel": "2021",
            "valeur": 137074
        },
        {
            "secteur_activite": "NON AGRICOLE",
            "region": "Oriental",
            "annuel": "2021",
            "valeur": 99087
        },
        {
            "secteur_activite": "NON AGRICOLE",
            "region": "Fès-Meknès",
            "annuel": "2021",
            "valeur": 88071
        },
        {
            "secteur_activite": "NON AGRICOLE",
            "region": "Rabat-Salé-Kénitra",
            "annuel": "2021",
            "valeur": 141113
        },
        {
            "secteur_activite": "NON AGRICOLE",
            "region": "Béni Mellal-Khénifra",
            "annuel": "2021",
            "valeur": 121229
        },
        {
            "secteur_activite": "NON AGRICOLE",
            "region": "Casablanca-Settat",
            "annuel": "2021",
            "valeur": 180130
        },
        {
            "secteur_activite": "NON AGRICOLE",
            "region": "Marrakech-Safi",
            "annuel": "2021",
            "valeur": 79013
        },
        {
            "secteur_activite": "NON AGRICOLE",
            "region": "Drâa-Tafilalet",
            "annuel": "2021",
            "valeur": 97172
        },
        {
            "secteur_activite": "NON AGRICOLE",
            "region": "Souss-Massa",
            "annuel": "2021",
            "valeur": 103826
        },
        {
            "secteur_activite": "NON AGRICOLE",
            "region": "Régions du Sud",
            "annuel": "2021",
            "valeur": 224290
        },
        {
            "secteur_activite": "AGRICOLE",
            "region": "Tanger-Tétouan-Al Hoceima",
            "annuel": "2022",
            "valeur": 29599
        },
        {
            "secteur_activite": "AGRICOLE",
            "region": "Oriental",
            "annuel": "2022",
            "valeur": 74184
        },
        {
            "secteur_activite": "AGRICOLE",
            "region": "Fès-Meknès",
            "annuel": "2022",
            "valeur": 52406
        },
        {
            "secteur_activite": "AGRICOLE",
            "region": "Rabat-Salé-Kénitra",
            "annuel": "2022",
            "valeur": 62643
        },
        {
            "secteur_activite": "AGRICOLE",
            "region": "Béni Mellal-Khénifra",
            "annuel": "2022",
            "valeur": 36720
        },
        {
            "secteur_activite": "AGRICOLE",
            "region": "Casablanca-Settat",
            "annuel": "2022",
            "valeur": 30752
        },
        {
            "secteur_activite": "AGRICOLE",
            "region": "Marrakech-Safi",
            "annuel": "2022",
            "valeur": 19073
        },
        {
            "secteur_activite": "AGRICOLE",
            "region": "Drâa-Tafilalet",
            "annuel": "2022",
            "valeur": 41092
        },
        {
            "secteur_activite": "AGRICOLE",
            "region": "Souss-Massa",
            "annuel": "2022",
            "valeur": 77861
        },
        {
            "secteur_activite": "AGRICOLE",
            "region": "Régions du Sud",
            "annuel": "2022",
            "valeur": 91158
        },
        {
            "secteur_activite": "NON AGRICOLE",
            "region": "Tanger-Tétouan-Al Hoceima",
            "annuel": "2022",
            "valeur": 146952
        },
        {
            "secteur_activite": "NON AGRICOLE",
            "region": "Oriental",
            "annuel": "2022",
            "valeur": 99423
        },
        {
            "secteur_activite": "NON AGRICOLE",
            "region": "Fès-Meknès",
            "annuel": "2022",
            "valeur": 94962
        },
        {
            "secteur_activite": "NON AGRICOLE",
            "region": "Rabat-Salé-Kénitra",
            "annuel": "2022",
            "valeur": 152669
        },
        {
            "secteur_activite": "NON AGRICOLE",
            "region": "Béni Mellal-Khénifra",
            "annuel": "2022",
            "valeur": 147464
        },
        {
            "secteur_activite": "NON AGRICOLE",
            "region": "Casablanca-Settat",
            "annuel": "2022",
            "valeur": 187446
        },
        {
            "secteur_activite": "NON AGRICOLE",
            "region": "Marrakech-Safi",
            "annuel": "2022",
            "valeur": 94194
        },
        {
            "secteur_activite": "NON AGRICOLE",
            "region": "Drâa-Tafilalet",
            "annuel": "2022",
            "valeur": 106321
        },
        {
            "secteur_activite": "NON AGRICOLE",
            "region": "Souss-Massa",
            "annuel": "2022",
            "valeur": 116042
        },
        {
            "secteur_activite": "NON AGRICOLE",
            "region": "Régions du Sud",
            "annuel": "2022",
            "valeur": 243399
        }
    ]
}