[
    {
        "nom": "cadre macro-économique - décisionnel",
        "libelle": "Cadre Macro-économique",
        "description": "Domaine concernant le cadre macro-économique et les indicateurs économiques",
        "roleAcces": [
            {
                "roleCode": "role_decideur",
                "niveauAcces": "lecture"
            }
        ],
        "actif": true
    },
    {
        "nom": "relations professionnelles et climat social - public",
        "libelle": "Relations Professionnelles et Climat Social",
        "description": "Domaine concernant les relations professionnelles et le climat social",
        "roleAcces": [
            {
                "roleCode": "role_public",
                "niveauAcces": "lecture"
            },
            {
                "roleCode": "role_decideur",
                "niveauAcces": "lecture"
            }
        ],
        "actif": true
    },
    {
        "nom": "employabilité et insertion professionnelle - public",
        "libelle": "Employabilité et Insertion Professionnelle",
        "description": "Version publique du domaine Employabilité et Insertion Professionnelle (indicateurs diffusables).",
        "roleAcces": [
            {
                "roleCode": "role_public",
                "niveauAcces": "lecture"
            },
            {
                "roleCode": "role_decideur",
                "niveauAcces": "lecture"
            }
        ],
        "actif": true
    },
    {
        "nom": "employabilité et insertion professionnelle - decisionnel",
        "libelle": "Employabilité et Insertion Professionnelle",
        "description": "Version décisionnelle interne du domaine Employabilité et Insertion Professionnelle (indicateurs non publics).",
        "roleAcces": [
            {
                "roleCode": "role_decideur",
                "niveauAcces": "lecture"
            }
        ],
        "actif": true
    },
    {
        "nom": "Offre de formation - public",
        "libelle": "Offre de Formation",
        "description": "Version publique du domaine Offre de formation (indicateurs diffusables).",
        "roleAcces": [
            {
                "roleCode": "role_public",
                "niveauAcces": "lecture"
            },
            {
                "roleCode": "role_decideur",
                "niveauAcces": "lecture"
            }
        ],
        "actif": true
    },
    {
        "nom": "Offre de travail - décisionnel",
        "libelle": "Offre de Travail",
        "description": "Version décisionnelle du domaine Offre de travail (indicateurs non publics).",
        "roleAcces": [
            {
                "roleCode": "role_decideur",
                "niveauAcces": "lecture"
            }
        ],
        "actif": true
    },
    {
        "nom": "Offre de travail - public",
        "libelle": "Offre de Travail",
        "description": "Version publique du domaine Offre de travail (indicateurs diffusables).",
        "roleAcces": [
            {
                "roleCode": "role_public",
                "niveauAcces": "lecture"
            },
            {
                "roleCode": "role_decideur",
                "niveauAcces": "lecture"
            }
        ],
        "actif": true
    },
    {
        "nom": "Intermédiation sur le marché du travail - public",
        "libelle": "Intermédiation sur le marché du travail",
        "description": "Version publique du domaine Intermédiation sur le marché du travail (indicateurs diffusables).",
        "roleAcces": [
            {
                "roleCode": "role_public",
                "niveauAcces": "lecture"
            },
            {
                "roleCode": "role_decideur",
                "niveauAcces": "lecture"
            }
        ],
        "actif": true
    },
    {
        "nom": "demande de travail - décisionnel",
        "libelle": "Demande de Travail",
        "description": "Version décisionnelle du domaine Demande de travail (accès interne).",
        "roleAcces": [
            {
                "roleCode": "role_decideur",
                "niveauAcces": "lecture"
            }
        ],
        "actif": true
    },
    {
        "nom": "demande de travail - public",
        "libelle": "Demande de Travail",
        "description": "Version publique du domaine Demande de travail (indicateurs diffusables).",
        "roleAcces": [
            {
                "roleCode": "role_public",
                "niveauAcces": "lecture"
            },
            {
                "roleCode": "role_decideur",
                "niveauAcces": "lecture"
            }
        ],
        "actif": true
    },
    {
        "nom": "Compétitivité et salaires - public",
        "libelle": "Compétitivité et Salaires",
        "description": "Version publique du domaine Compétitivité et salaires.",
        "roleAcces": [
            {
                "roleCode": "role_public",
                "niveauAcces": "lecture"
            },
            {
                "roleCode": "role_decideur",
                "niveauAcces": "lecture"
            }
        ],
        "actif": true
    }
]